scrapscript.py
scrapscript-0.1.1.dist-info/LICENSE
scrapscript-0.1.1.dist-info/METADATA
scrapscript-0.1.1.dist-info/WHEEL
scrapscript-0.1.1.dist-info/entry_points.txt
scrapscript-0.1.1.dist-info/RECORD
