Metadata-Version: 2.1
Name: scrapscript
Version: 0.1.1
Summary: Scrapscript interpreter
Home-page: https://github.com/tekknolagi/scrapscript
License: MIT
Keywords: scrapscript,interpreter
Author: Max Bernstein
Author-email: python@bernsteinbear.com
Requires-Python: >=3.8
Classifier: Intended Audience :: Developers
Classifier: License :: OSI Approved :: MIT License
Classifier: Programming Language :: Python
Classifier: Programming Language :: Python :: 3
Classifier: Programming Language :: Python :: 3.8
Classifier: Programming Language :: Python :: 3.9
Classifier: Programming Language :: Python :: 3.10
Classifier: Programming Language :: Python :: 3.11
Classifier: Programming Language :: Python :: 3.12
Classifier: Topic :: Software Development
Project-URL: Repository, https://github.com/tekknolagi/scrapscript
